odoo/addons/mail_parent_recipient/README.rst
odoo/addons/mail_parent_recipient/__init__.py
odoo/addons/mail_parent_recipient/__manifest__.py
odoo/addons/mail_parent_recipient/i18n/mail_parent_recipient.pot
odoo/addons/mail_parent_recipient/models/__init__.py
odoo/addons/mail_parent_recipient/models/mail_template.py
odoo/addons/mail_parent_recipient/models/res_config.py
odoo/addons/mail_parent_recipient/readme/CONTRIBUTORS.rst
odoo/addons/mail_parent_recipient/readme/CREDITS.rst
odoo/addons/mail_parent_recipient/readme/DESCRIPTION.rst
odoo/addons/mail_parent_recipient/static/description/icon.png
odoo/addons/mail_parent_recipient/static/description/index.html
odoo/addons/mail_parent_recipient/tests/__init__.py
odoo/addons/mail_parent_recipient/tests/test_mail_parent_recipient.py
odoo/addons/mail_parent_recipient/views/res_config_views.xml
odoo_addon_mail_parent_recipient-15.0.1.0.0.4.dist-info/METADATA
odoo_addon_mail_parent_recipient-15.0.1.0.0.4.dist-info/WHEEL
odoo_addon_mail_parent_recipient-15.0.1.0.0.4.dist-info/top_level.txt
odoo_addon_mail_parent_recipient-15.0.1.0.0.4.dist-info/RECORD
